cli/main.py
engine/audit.py
engine/models.py
engine/renderer.py
engine/validator.py
supabase_client/client.py
supabase_client/templates.py
sentineliam-0.1.1.dist-info/METADATA
sentineliam-0.1.1.dist-info/WHEEL
sentineliam-0.1.1.dist-info/entry_points.txt
sentineliam-0.1.1.dist-info/top_level.txt
sentineliam-0.1.1.dist-info/RECORD
